{
    "tweet": "Finished Ratchet and Clank before work so not even eight o'clock and today has peaked already.",
    "user_name": "Steve",
    "user_id": 18839911,
    "user_location": "Glasgow",
    "address": "Scotland, UK",
    "tweet_id": "728111743377891329",
    "country": "UK",
    "geometry": {
        "type": "Point",
        "coordinates": [
            -4.4031651,
            55.8553334
        ]
    },
    "state": "Scotland"
},
{
    "tweet": "Vou ver Ratchet and Clank ao cinema! \ud83d\ude09",
    "user_name": "Regedit.exe",
    "user_id": 1187219803,
    "user_location": "Portugal",
    "address": "Centro, Portugal",
    "tweet_id": "728274365993848832",
    "country": "Portugal",
    "geometry": {
        "type": "Point",
        "coordinates": [
            -8.09536454,
            40.76876063
        ]
    },
    "state": "Centro"
},
{
    "tweet": "LAST NIGHT \ud83d\ude01\ud83d\ude01\ud83d\ude01 #throwbackthursday #quitplayinggameswithmyheart #thebaddest #teamnatural #ratchet\u2026 https://t.co/yUBHs75I13",
    "user_name": "TheSheenBee",
    "user_id": 91309836,
    "user_location": null,
    "tweet_id": "728521708873854976",
    "geometry": {
        "type": "Point",
        "coordinates": [
            123.93413431,
            10.3265739
        ]
    }
},
{
    "tweet": "\ud83d\udc6b \u2605 Ratchet &amp; Clank (with Frans at @cgvblitz) \u2014 https://t.co/kX7J1dG1ZX",
    "user_name": "Jennifer Gunawan",
    "user_id": 248587859,
    "user_location": "Parent's Heart \u2665",
    "tweet_id": "728537673409789952",
    "geometry": {
        "type": "Point",
        "coordinates": [
            106.79096,
            -6.17737
        ]
    }
},
{
    "tweet": "Looking good.... Actually still ratchet tho xD @ Toronto Marriott Bloor Yorkville Hotel https://t.co/htxwBbin0y",
    "user_name": "E-Word",
    "user_id": 393774744,
    "user_location": "Toronto",
    "address": "Ontario, Canada",
    "tweet_id": "728731342905581568",
    "country": "Canada",
    "geometry": {
        "type": "Point",
        "coordinates": [
            -79.38482,
            43.67087
        ]
    },
    "state": "Ontario"
},
{
    "tweet": "Saw these studs today! Cuties! Love them so much!\ud83d\ude18\ud83d\udc95 (excuse my ratchet self\ud83d\ude01) https://t.co/HZqmGMobwx",
    "user_name": "tayee",
    "user_id": 2314691804,
    "user_location": "on my couch",
    "tweet_id": "728746703013076992",
    "geometry": {
        "type": "Point",
        "coordinates": [
            -122.3126059,
            47.2751791
        ]
    }
},
{
    "tweet": "I'm at AMC Burbank 16 - @amctheatres for Ratchet and Clank in Burbank, CA https://t.co/P9WpEGWXAP",
    "user_name": "Anthony Armstrong",
    "user_id": 391179187,
    "user_location": "West Coast",
    "tweet_id": "728786628769099777",
    "geometry": {
        "type": "Point",
        "coordinates": [
            -118.31200361,
            34.1819236
        ]
    }
},
{
    "tweet": "This now, Civil War later xD (@ AMC Loews Woodinville 12 - @amctheatres for Ratchet and Clank 3D in Woodinville, WA) https://t.co/c4hPrUPphT",
    "user_name": "Jordan Rinehart",
    "user_id": 82775305,
    "user_location": "Close to Seattle, WA",
    "tweet_id": "728821411029094401",
    "geometry": {
        "type": "Point",
        "coordinates": [
            -122.15460062,
            47.75590845
        ]
    }
},
{
    "tweet": "I'm at @Cinesystem for Ratchet and Clank 3D in Praia Grande, SP https://t.co/ijv6RGjjsp",
    "user_name": "Vinicius Martins",
    "user_id": 55906457,
    "user_location": "Brazil",
    "address": "SP, Brasil",
    "tweet_id": "729020425737474048",
    "country": "Brasil",
    "geometry": {
        "type": "Point",
        "coordinates": [
            -46.40818119,
            -23.99683868
        ]
    },
    "state": "SP"
},
{
    "tweet": "What a good time we had at the Ratchet &amp; Clank this morning! #movie #R&amp;C #rainmakerentertainment\u2026 https://t.co/PvNQcXNlba",
    "user_name": "Rainmaker Ent",
    "user_id": 334832804,
    "user_location": "Vancouver, BC",
    "tweet_id": "729030996067266561",
    "geometry": {
        "type": "Point",
        "coordinates": [
            -123.10669748,
            49.28019353
        ]
    }
},
{
    "tweet": "Having a blast at the Rainmaker Entertainment screening of Ratchet and Clank! Did you see it\u2026 https://t.co/ghRW0UL1hk",
    "user_name": "Rainmaker Ent",
    "user_id": 334832804,
    "user_location": "Vancouver, BC",
    "tweet_id": "729031494635761665",
    "geometry": {
        "type": "Point",
        "coordinates": [
            -123.10669748,
            49.28019353
        ]
    }
},
{
    "tweet": "I'm at Cinemark for Ratchet and Clank in Salvador, BA https://t.co/tsQvcbLkwr",
    "user_name": "RENATA (TIM BETA)",
    "user_id": 164481328,
    "user_location": "SALVADOR",
    "address": "BA, Brasil",
    "tweet_id": "729033144544968706",
    "country": "Brasil",
    "geometry": {
        "type": "Point",
        "coordinates": [
            -38.45503045,
            -12.97834735
        ]
    },
    "state": "BA"
},
{
    "tweet": "I'm at @UCICinemas for Ratchet and Clank 3D in Fortaleza, CE w/ @adrc_costa https://t.co/4ugGWlre5u",
    "user_name": "Binho (Beta)RT",
    "user_id": 104535814,
    "user_location": "Brasil",
    "address": "CE, Brasil",
    "tweet_id": "729073497624985602",
    "country": "Brasil",
    "geometry": {
        "type": "Point",
        "coordinates": [
            -38.48839045,
            -3.75729983
        ]
    },
    "state": "CE"
},
{
    "tweet": "I'm at AMC Ford City 14 - @amctheatres for Ratchet and Clank 3D in Chicago, IL https://t.co/fu6MyZyjH7",
    "user_name": "Beautiful Savage",
    "user_id": 274852801,
    "user_location": null,
    "address": "Illinois, United States of America",
    "tweet_id": "729107853450072065",
    "country": "United States of America",
    "geometry": {
        "type": "Point",
        "coordinates": [
            -87.73340464,
            41.75380964
        ]
    },
    "state": "Illinois"
},
{
    "tweet": "I'm at Cinemark for Ratchet and Clank 3D in Bras\u00edlia, DF https://t.co/vTBna4ULK3",
    "user_name": "Isabella Oliveira",
    "user_id": 371746140,
    "user_location": "BSB, Brasil",
    "address": "DF, Brasil",
    "tweet_id": "729109382626213889",
    "country": "Brasil",
    "geometry": {
        "type": "Point",
        "coordinates": [
            -48.0440712,
            -15.84155439
        ]
    },
    "state": "DF"
},
{
    "tweet": "I think I\u2019m going to buy Ratchet &amp; Clank today",
    "user_name": "unrecognized selecta",
    "user_id": 41151264,
    "user_location": "Crushin' on Cocoa Pebbles!",
    "address": "Pennsylvania, United States of America",
    "tweet_id": "729310466955202562",
    "country": "United States of America",
    "geometry": {
        "type": "Point",
        "coordinates": [
            -79.97028147,
            40.28752891
        ]
    },
    "state": "Pennsylvania"
},
{
    "tweet": "Kid Franklin says the  \"Ratchet and Clank\" movie is awesome - now you know. (@ Landmark Cinemas Orl\u00e9ans 10) https://t.co/nmfLYzh7SN",
    "user_name": "Franklin on Food",
    "user_id": 498358653,
    "user_location": "Ottawa, Ontario, Canada",
    "address": "Ontario, Canada",
    "tweet_id": "729388679765037056",
    "country": "Canada",
    "geometry": {
        "type": "Point",
        "coordinates": [
            -75.51569626,
            45.44873776
        ]
    },
    "state": "Ontario"
},
{
    "tweet": "Now for some Lombax! (@ Grand 10 Cinema for Ratchet and Clank in Kelowna, BC) https://t.co/nm5qcQI31O",
    "user_name": "Kendra Kirai",
    "user_id": 252336282,
    "user_location": "Canada",
    "tweet_id": "729524089736581120",
    "geometry": {
        "type": "Point",
        "coordinates": [
            -119.40542221,
            49.90248518
        ]
    }
},
{
    "tweet": "I'm at UCI Kinoplex - @ucicinemas for Ratchet and Clank 3D in Recife, PE https://t.co/pHJpQyMGJI",
    "user_name": "Diego Salatiel",
    "user_id": 127937023,
    "user_location": "Apipucos, Recife",
    "address": "PE, Brasil",
    "tweet_id": "730429635184476160",
    "country": "Brasil",
    "geometry": {
        "type": "Point",
        "coordinates": [
            -34.91260886,
            -8.03705908
        ]
    },
    "state": "PE"
},
{
    "tweet": "#ventas #pymes #costarica RATCHET &amp; CLANK ALL 4ONE FAVORITOS https://t.co/RXh0XKJvGw",
    "user_name": "Nidux Comercial",
    "user_id": 709833275666259968,
    "user_location": null,
    "address": "Provincia San Jos\u00e9, Costa Rica",
    "tweet_id": "730457453310025728",
    "country": "Costa Rica",
    "geometry": {
        "type": "Point",
        "coordinates": [
            -84.08333,
            9.93333
        ]
    },
    "state": "Provincia San Jos\u00e9"
},
{
    "tweet": "Ratchet &amp; Clank!!! (@ Cinemark for Ratchet and Clank 3D in Curitiba, PR) https://t.co/EdHjR9lnkh",
    "user_name": "Rafael A. Calomeno",
    "user_id": 52277047,
    "user_location": "Brazil",
    "address": "PR, Brasil",
    "tweet_id": "730495959155781632",
    "country": "Brasil",
    "geometry": {
        "type": "Point",
        "coordinates": [
            -49.31638241,
            -25.43552376
        ]
    },
    "state": "PR"
},
{
    "tweet": "I'm at North Shopping Fortaleza for Ratchet and Clank in Fortaleza, CE https://t.co/3WwxDDvSzm",
    "user_name": "Marcio Paulo",
    "user_id": 141016811,
    "user_location": "Fortaleza - Ce",
    "address": "CE, Brasil",
    "tweet_id": "730978046761684992",
    "country": "Brasil",
    "geometry": {
        "type": "Point",
        "coordinates": [
            -38.56604576,
            -3.73544907
        ]
    },
    "state": "CE"
},
{
    "tweet": "@Sky_Armada I've been playing Dark Souls 3 and Ratchet and Clank. Just burned Uncharted 4, too. Even 100%'d Hatoful Boyfriend for shiggles.",
    "user_name": "Wanderpus",
    "user_id": 111306087,
    "user_location": "Derpville",
    "tweet_id": "731216074910240769",
    "geometry": {
        "type": "Point",
        "coordinates": [
            -122.09962249,
            47.68357386
        ]
    }
},
{
    "tweet": "Movie date with this guy \ud83d\udc95 he's treating me to a screening of Ratchet &amp; Clank with his birthday\u2026 https://t.co/t89Kjl1Kqc",
    "user_name": "Michelle Mackintosh",
    "user_id": 14092408,
    "user_location": "Calgary, AB ",
    "tweet_id": "731242269722873856",
    "geometry": {
        "type": "Point",
        "coordinates": [
            -114.07439699,
            50.99553659
        ]
    }
},
{
    "tweet": "Mi hermano birriando Ratchet and Clank PS4 @ Albrook Mall, Panama City https://t.co/naJBXPUaTC",
    "user_name": "Alejandro Mena Mej\u00eda",
    "user_id": 94842633,
    "user_location": "Arraij\u00e1n, Panam\u00e1",
    "address": "Provincia de Panam\u00e1, Panam\u00e1",
    "tweet_id": "731255656175435778",
    "country": "Panam\u00e1",
    "geometry": {
        "type": "Point",
        "coordinates": [
            -79.55238058,
            8.97399561
        ]
    },
    "state": "Provincia de Panam\u00e1"
},
{
    "tweet": "Movie time with my little girl. (@ Epic Theatres of Palm Coast for Ratchet and Clank in Palm Coast, FL) https://t.co/AzsIXYPWta",
    "user_name": "\u2623Shane Wood\u2623",
    "user_id": 51878528,
    "user_location": "Florida",
    "address": "Florida, United States of America",
    "tweet_id": "731865821971120128",
    "country": "United States of America",
    "geometry": {
        "type": "Point",
        "coordinates": [
            -81.20395303,
            29.4825404
        ]
    },
    "state": "Florida"
},
{
    "tweet": "Woo! Beat Ratchet and Clank! And I got all the gold bolts!",
    "user_name": "Mintz",
    "user_id": 97980241,
    "user_location": null,
    "address": "Michigan, United States of America",
    "tweet_id": "731897290789511168",
    "country": "United States of America",
    "geometry": {
        "type": "Point",
        "coordinates": [
            -83.3191047,
            42.4313169
        ]
    },
    "state": "Michigan"
},
{
    "tweet": "Ratchet!! \ud83d\ude0d (@ Blue Oaks Cinema 16 - @cinemark for Ratchet and Clank in Rocklin, CA) https://t.co/1MpUXlvEUW",
    "user_name": "Jose Castaneda",
    "user_id": 175522943,
    "user_location": "Roseville, CA",
    "tweet_id": "731900704953118720",
    "geometry": {
        "type": "Point",
        "coordinates": [
            -121.29374027,
            38.7974769
        ]
    }
},
{
    "tweet": "Watching Ratchet &amp; Clank (at @voxcinemasoman) \u2014 https://t.co/Poytx5tQuq",
    "user_name": "developar",
    "user_id": 8054792,
    "user_location": "Oman ",
    "address": "\u0645\u062d\u0627\u0641\u0638\u0629 \u0645\u0633\u0642\u0637, \u0639\u0645\u0627\u0646",
    "tweet_id": "733597303596978176",
    "country": "\u0639\u0645\u0627\u0646",
    "geometry": {
        "type": "Point",
        "coordinates": [
            58.49019,
            23.60899
        ]
    },
    "state": "\u0645\u062d\u0627\u0641\u0638\u0629 \u0645\u0633\u0642\u0637"
},
{
    "geometry": {
        "type": "Point",
        "coordinates": [
            -8.09536454,
            40.76876063
        ]
    },
    "state": "Centro",
    "user_name": "Regedit.exe",
    "tweet": "Vou ver Ratchet and Clank ao cinema! \ud83d\ude09",
    "user_id": 1187219803,
    "country": "Portugal",
    "user_location": "Portugal",
    "tweet_id": "728274365993848832",
    "address": "Centro, Portugal"
},
{
    "geometry": {
        "type": "Point",
        "coordinates": [
            106.79096,
            -6.17737
        ]
    },
    "user_name": "Jennifer Gunawan",
    "tweet": "\ud83d\udc6b \u2605 Ratchet &amp; Clank (with Frans at @cgvblitz) \u2014 https://t.co/kX7J1dG1ZX",
    "user_id": 248587859,
    "user_location": "Parent's Heart \u2665",
    "tweet_id": "728537673409789952"
},
{
    "geometry": {
        "type": "Point",
        "coordinates": [
            106.60631,
            -6.22862
        ]
    },
    "user_name": "Rinda Ashiami",
    "tweet": "Nemenin 3 K nonton film \"Rachet and Clank\" \ud83d\ude00\ud83d\ude04 (with Chika, keisha, and Satrio at Cinemaxx Junior) [pic] \u2014 https://t.co/OTdj1tT01U",
    "user_id": 88450847,
    "user_location": "Under God's protection.",
    "tweet_id": "728581268422545408"
},
{
    "geometry": {
        "type": "Point",
        "coordinates": [
            -6.64677894,
            55.20400164
        ]
    },
    "state": "Northern Ireland",
    "user_name": "Clinton  K",
    "tweet": "From #ClanK here at #Portrush\nwe hope you and your clan are safe and\u2026 https://t.co/XUZ4D8k1nJ",
    "user_id": 62101442,
    "country": "UK",
    "user_location": "@BelieversBcraft",
    "tweet_id": "728673553583886336",
    "address": "Northern Ireland, UK"
},
{
    "geometry": {
        "type": "Point",
        "coordinates": [
            -118.31200361,
            34.1819236
        ]
    },
    "user_name": "Anthony Armstrong",
    "tweet": "I'm at AMC Burbank 16 - @amctheatres for Ratchet and Clank in Burbank, CA https://t.co/P9WpEGWXAP",
    "user_id": 391179187,
    "user_location": "West Coast",
    "tweet_id": "728786628769099777"
},
{
    "geometry": {
        "type": "Point",
        "coordinates": [
            -122.15460062,
            47.75590845
        ]
    },
    "state": "West Bengal",
    "user_name": "Ryan Basu",
    "tweet": "Playing some Ratchet &amp; Clank.\n#videogames #gaming #retrogaming #retrocollective #playstation\u2026 https://t.co/uZagy3lTWP",
    "user_id": 3063151545,
    "country": "India",
    "user_location": "Kolkata, India",
    "tweet_id": "728890321942151168",
    "address": "West Bengal, India"
},
{
    "geometry": {
        "type": "Point",
        "coordinates": [
            -46.40818119,
            -23.99683868
        ]
    },
    "state": "SP",
    "user_name": "Vinicius Martins",
    "tweet": "I'm at @Cinesystem for Ratchet and Clank 3D in Praia Grande, SP https://t.co/ijv6RGjjsp",
    "user_id": 55906457,
    "country": "Brasil",
    "user_location": "Brazil",
    "tweet_id": "729020425737474048",
    "address": "SP, Brasil"
},
{
    "geometry": {
        "type": "Point",
        "coordinates": [
            -123.10669748,
            49.28019353
        ]
    },
    "user_name": "Rainmaker Ent",
    "tweet": "What a good time we had at the Ratchet &amp; Clank this morning! #movie #R&amp;C #rainmakerentertainment\u2026 https://t.co/PvNQcXNlba",
    "user_id": 334832804,
    "user_location": "Vancouver, BC",
    "tweet_id": "729030996067266561"
},
{
    "geometry": {
        "type": "Point",
        "coordinates": [
            -123.10669748,
            49.28019353
        ]
    },
    "user_name": "Rainmaker Ent",
    "tweet": "Having a blast at the Rainmaker Entertainment screening of Ratchet and Clank! Did you see it\u2026 https://t.co/ghRW0UL1hk",
    "user_id": 334832804,
    "user_location": "Vancouver, BC",
    "tweet_id": "729031494635761665"
},
{
    "geometry": {
        "type": "Point",
        "coordinates": [
            -38.45503045,
            -12.97834735
        ]
    },
    "state": "BA",
    "user_name": "RENATA (TIM BETA)",
    "tweet": "I'm at Cinemark for Ratchet and Clank in Salvador, BA https://t.co/tsQvcbLkwr",
    "user_id": 164481328,
    "country": "Brasil",
    "user_location": "SALVADOR",
    "tweet_id": "729033144544968706",
    "address": "BA, Brasil"
},
{
    "geometry": {
        "type": "Point",
        "coordinates": [
            -38.48839045,
            -3.75729983
        ]
    },
    "state": "Ontario",
    "user_name": "Paakkonen  Photo",
    "tweet": "Finish off date day with Gaeb with Ratchet and Clank... #kids #grandkidsarethebest @ Landmark\u2026 https://t.co/tczjL9M1ag",
    "user_id": 17735965,
    "country": "Canada",
    "user_location": "\u00dcT: 43.680201,-79.678514",
    "tweet_id": "729074757220454400",
    "address": "Ontario, Canada"
},
{
    "geometry": {
        "type": "Point",
        "coordinates": [
            -87.73340464,
            41.75380964
        ]
    },
    "state": "Illinois",
    "user_name": "Beautiful Savage",
    "tweet": "I'm at AMC Ford City 14 - @amctheatres for Ratchet and Clank 3D in Chicago, IL https://t.co/fu6MyZyjH7",
    "user_id": 274852801,
    "country": "United States of America",
    "user_location": null,
    "tweet_id": "729107853450072065",
    "address": "Illinois, United States of America"
},
{
    "geometry": {
        "type": "Point",
        "coordinates": [
            -48.0440712,
            -15.84155439
        ]
    },
    "state": "DF",
    "user_name": "Isabella Oliveira",
    "tweet": "I'm at Cinemark for Ratchet and Clank 3D in Bras\u00edlia, DF https://t.co/vTBna4ULK3",
    "user_id": 371746140,
    "country": "Brasil",
    "user_location": "BSB, Brasil",
    "tweet_id": "729109382626213889",
    "address": "DF, Brasil"
},
{
    "geometry": {
        "type": "Point",
        "coordinates": [
            -79.97028147,
            40.28752891
        ]
    },
    "state": "Pennsylvania",
    "user_name": "unrecognized selecta",
    "tweet": "I think I\u2019m going to buy Ratchet &amp; Clank today",
    "user_id": 41151264,
    "country": "United States of America",
    "user_location": "Crushin' on Cocoa Pebbles!",
    "tweet_id": "729310466955202562",
    "address": "Pennsylvania, United States of America"
},
{
    "geometry": {
        "type": "Point",
        "coordinates": [
            -75.51569626,
            45.44873776
        ]
    },
    "state": "Ontario",
    "user_name": "Franklin on Food",
    "tweet": "Kid Franklin says the  \"Ratchet and Clank\" movie is awesome - now you know. (@ Landmark Cinemas Orl\u00e9ans 10) https://t.co/nmfLYzh7SN",
    "user_id": 498358653,
    "country": "Canada",
    "user_location": "Ottawa, Ontario, Canada",
    "tweet_id": "729388679765037056",
    "address": "Ontario, Canada"
},
{
    "geometry": {
        "type": "Point",
        "coordinates": [
            -119.40542221,
            49.90248518
        ]
    },
    "user_name": "Kendra Kirai",
    "tweet": "Now for some Lombax! (@ Grand 10 Cinema for Ratchet and Clank in Kelowna, BC) https://t.co/nm5qcQI31O",
    "user_id": 252336282,
    "user_location": "Canada",
    "tweet_id": "729524089736581120"
},
{
    "geometry": {
        "type": "Point",
        "coordinates": [
            -34.91260886,
            -8.03705908
        ]
    },
    "state": "PE",
    "user_name": "Diego Salatiel",
    "tweet": "I'm at UCI Kinoplex - @ucicinemas for Ratchet and Clank 3D in Recife, PE https://t.co/pHJpQyMGJI",
    "user_id": 127937023,
    "country": "Brasil",
    "user_location": "Apipucos, Recife",
    "tweet_id": "730429635184476160",
    "address": "PE, Brasil"
},
{
    "geometry": {
        "type": "Point",
        "coordinates": [
            -84.08333,
            9.93333
        ]
    },
    "state": "Scotland",
    "user_name": "GAME Glasgow UnionSt",
    "tweet": "Ratchet &amp; Clank was the best-selling game on PlayStation Store last month https://t.co/NVzhHZsL9l https://t.co/3k4ctOy539",
    "user_id": 624771315,
    "country": "UK",
    "user_location": "Glasgow, Scotland",
    "tweet_id": "730476365699420160",
    "address": "Scotland, UK"
},
{
    "geometry": {
        "type": "Point",
        "coordinates": [
            -49.31638241,
            -25.43552376
        ]
    },
    "state": "PR",
    "user_name": "Rafael A. Calomeno",
    "tweet": "Ratchet &amp; Clank!!! (@ Cinemark for Ratchet and Clank 3D in Curitiba, PR) https://t.co/EdHjR9lnkh",
    "user_id": 52277047,
    "country": "Brasil",
    "user_location": "Brazil",
    "tweet_id": "730495959155781632",
    "address": "PR, Brasil"
},
{
    "geometry": {
        "type": "Point",
        "coordinates": [
            -38.56604576,
            -3.73544907
        ]
    },
    "user_name": "Philip C. Robinson",
    "tweet": "I'm at Regal Cinemas Kansas City 18 - @regalmovies for Ratchet and Clank in Kansas City, MO https://t.co/mPQJezZ84v",
    "user_id": 6286022,
    "user_location": "Smithville MO USA",
    "tweet_id": "730982111583293440"
},
{
    "geometry": {
        "type": "Point",
        "coordinates": [
            -122.09962249,
            47.68357386
        ]
    },
    "user_name": "Wanderpus",
    "tweet": "@Sky_Armada I've been playing Dark Souls 3 and Ratchet and Clank. Just burned Uncharted 4, too. Even 100%'d Hatoful Boyfriend for shiggles.",
    "user_id": 111306087,
    "user_location": "Derpville",
    "tweet_id": "731216074910240769"
},
{
    "geometry": {
        "type": "Point",
        "coordinates": [
            -114.07439699,
            50.99553659
        ]
    },
    "user_name": "Michelle Mackintosh",
    "tweet": "Movie date with this guy \ud83d\udc95 he's treating me to a screening of Ratchet &amp; Clank with his birthday\u2026 https://t.co/t89Kjl1Kqc",
    "user_id": 14092408,
    "user_location": "Calgary, AB ",
    "tweet_id": "731242269722873856"
},
{
    "geometry": {
        "type": "Point",
        "coordinates": [
            -79.55238058,
            8.97399561
        ]
    },
    "user_name": "Kelly's Chaos",
    "tweet": "Date with my lil guy (@ CineLux Tennant Station Stadium 11 for Ratchet and Clank in Morgan Hill, CA) https://t.co/wvGRWaoUR6",
    "user_id": 15743290,
    "user_location": "San Jose, CA",
    "tweet_id": "731544802181955584"
},
{
    "geometry": {
        "type": "Point",
        "coordinates": [
            -78.31840994,
            44.30403714
        ]
    },
    "state": "Ontario",
    "user_name": "Michelle Ferreri",
    "tweet": "THEY LOVED IT!! Clank was the best character\ud83d\ude09\u2764\ufe0f great job @dkayevo \n#ratchetandclank\u2026 https://t.co/p74yOC01qr",
    "user_id": 739149720,
    "country": "Canada",
    "user_location": "Lakefield ON",
    "tweet_id": "731628724899201024",
    "address": "Ontario, Canada"
},
{
    "geometry": {
        "type": "Point",
        "coordinates": [
            -81.20395303,
            29.4825404
        ]
    },
    "state": "Florida",
    "user_name": "\u2623Shane Wood\u2623",
    "tweet": "Movie time with my little girl. (@ Epic Theatres of Palm Coast for Ratchet and Clank in Palm Coast, FL) https://t.co/AzsIXYPWta",
    "user_id": 51878528,
    "country": "United States of America",
    "user_location": "Florida",
    "tweet_id": "731865821971120128",
    "address": "Florida, United States of America"
},
{
    "geometry": {
        "type": "Point",
        "coordinates": [
            -83.3191047,
            42.4313169
        ]
    },
    "state": "Michigan",
    "user_name": "Mintz",
    "tweet": "Woo! Beat Ratchet and Clank! And I got all the gold bolts!",
    "user_id": 97980241,
    "country": "United States of America",
    "user_location": null,
    "tweet_id": "731897290789511168",
    "address": "Michigan, United States of America"
},
{
    "geometry": {
        "type": "Point",
        "coordinates": [
            -121.29374027,
            38.7974769
        ]
    },
    "user_name": "Jose Castaneda",
    "tweet": "Ratchet!! \ud83d\ude0d (@ Blue Oaks Cinema 16 - @cinemark for Ratchet and Clank in Rocklin, CA) https://t.co/1MpUXlvEUW",
    "user_id": 175522943,
    "user_location": "Roseville, CA",
    "tweet_id": "731900704953118720"
},
{
    "geometry": {
        "type": "Point",
        "coordinates": [
            -1.67551152,
            54.95160553
        ]
    },
    "state": "England",
    "user_name": "Paul Ingham",
    "tweet": "I'm starting to regret skipping Ratchet and Clank: A Crack In Time",
    "user_id": 279219517,
    "country": "UK",
    "user_location": "Gateshead, United Kingdom",
    "tweet_id": "732347056447234048",
    "address": "England, UK"
},
{
    "geometry": {
        "type": "Point",
        "coordinates": [
            -73.98905285,
            40.75703458
        ]
    },
    "state": "New York",
    "user_name": "Joshua Nicholson",
    "tweet": "Ratchet and Clank (@ Regal Cinemas E-Walk 13 &amp; RPX - @regalmovies for Ratchet and Clank in New York, NY) https://t.co/jKumDpc0Ph",
    "user_id": 33472977,
    "country": "United States of America",
    "user_location": "New York City",
    "tweet_id": "732751710335143936",
    "address": "New York, United States of America"
},
{
    "geometry": {
        "type": "Point",
        "coordinates": [
            -35.69889307,
            -9.62658181
        ]
    },
    "state": "AL",
    "user_name": "Marcelo A (tim beta)",
    "tweet": "I'm at @Cinesystem for Ratchet and Clank in Macei\u00f3, Alagoas https://t.co/ZfqgF1KYpw",
    "user_id": 47492048,
    "country": "Brasil",
    "user_location": "Maceio/Al Brazil",
    "tweet_id": "732985267401940992",
    "address": "AL, Brasil"
},
{
    "geometry": {
        "type": "Point",
        "coordinates": [
            -123.04534078,
            44.0748606
        ]
    },
    "user_name": "Kurt Liedtke",
    "tweet": "Seeing ratchet and clank the movie since I worked on five of the ratchet and clank video games. As expected,... https://t.co/ygnzqpBJhx",
    "user_id": 51543737,
    "user_location": "Lakeview, OR",
    "tweet_id": "733000809907126273"
},
{
    "geometry": {
        "type": "Point",
        "coordinates": [
            -90.4176728,
            38.6989202
        ]
    },
    "user_name": "Rich Gould",
    "tweet": "Clank goes the leather of Diaz ... gotta REALLY hit well to play when peralta get back #cardinals #mlb",
    "user_id": 1311511520,
    "user_location": "St. Louis, MO",
    "tweet_id": "733090580918611969"
},
{
    "geometry": {
        "type": "Point",
        "coordinates": [
            -122.09972195,
            47.68370022
        ]
    },
    "user_name": "Wanderpus",
    "tweet": "Dark Souls 3 and Ratchet &amp; Clank complete! Now to tackle some older backlog- Witcher 3 and Bloodborne up next. Gaaaaaaaaemz",
    "user_id": 111306087,
    "user_location": "Derpville",
    "tweet_id": "733213398029074432"
},
{
    "geometry": {
        "type": "Point",
        "coordinates": [
            58.49019,
            23.60899
        ]
    },
